{
  "generated": "2026-06-17",
  "scanned": 1929,
  "qualified": 85,
  "shown": 60,
  "counts": {
    "total": 60,
    "hyper": 12,
    "high": 10,
    "moderate": 8,
    "low": 30
  },
  "protocols": [
    {
      "rank": 1,
      "name": "Limitless Exchange",
      "symbol": "LMTS",
      "category": "Prediction Market",
      "tier": "HYPERLIQUID-GRADE",
      "earnings_yield_pct": 554.8,
      "annualized_revenue": 62254242,
      "mcap": 11220947
    },
    {
      "rank": 2,
      "name": "Collector Crypt",
      "symbol": "CARDS",
      "category": "Physical TCG",
      "tier": "HYPERLIQUID-GRADE",
      "earnings_yield_pct": 188.41,
      "annualized_revenue": 119779641,
      "mcap": 63574789
    },
    {
      "rank": 3,
      "name": "ORE Protocol",
      "symbol": "ORE",
      "category": "Gamified Mining",
      "tier": "HYPERLIQUID-GRADE",
      "earnings_yield_pct": 111.12,
      "annualized_revenue": 42595026,
      "mcap": 38332215
    },
    {
      "rank": 4,
      "name": "Bankr",
      "symbol": "BNKR",
      "category": "Interface",
      "tier": "HYPERLIQUID-GRADE",
      "earnings_yield_pct": 80.37,
      "annualized_revenue": 38657965,
      "mcap": 48097669
    },
    {
      "rank": 5,
      "name": "USD AI",
      "symbol": "CHIP",
      "category": "RWA Lending",
      "tier": "HYPERLIQUID-GRADE",
      "earnings_yield_pct": 54.47,
      "annualized_revenue": 37563391,
      "mcap": 68964416
    },
    {
      "rank": 6,
      "name": "THORSwap",
      "symbol": "THOR",
      "category": "DEX Aggregator",
      "tier": "HYPERLIQUID-GRADE",
      "earnings_yield_pct": 39.8,
      "annualized_revenue": 3670318,
      "mcap": 9222536
    },
    {
      "rank": 7,
      "name": "Gains Network",
      "symbol": "GNS",
      "category": "Derivatives",
      "tier": "HYPERLIQUID-GRADE",
      "earnings_yield_pct": 30.73,
      "annualized_revenue": 4291415,
      "mcap": 13966423
    },
    {
      "rank": 8,
      "name": "Overtime",
      "symbol": "OVER",
      "category": "Prediction Market",
      "tier": "HYPERLIQUID-GRADE",
      "earnings_yield_pct": 29.6,
      "annualized_revenue": 2165387,
      "mcap": 7315925
    },
    {
      "rank": 9,
      "name": "Inverse Finance FiRM",
      "symbol": "INV",
      "category": "CDP",
      "tier": "HYPERLIQUID-GRADE",
      "earnings_yield_pct": 27.7,
      "annualized_revenue": 2048940,
      "mcap": 7395961
    },
    {
      "rank": 10,
      "name": "Dolomite",
      "symbol": "DOLO",
      "category": "Lending",
      "tier": "HYPERLIQUID-GRADE",
      "earnings_yield_pct": 25.07,
      "annualized_revenue": 2998925,
      "mcap": 11961637
    },
    {
      "rank": 11,
      "name": "DEXTools",
      "symbol": "DEXT",
      "category": "Coins Tracker",
      "tier": "HYPERLIQUID-GRADE",
      "earnings_yield_pct": 22.01,
      "annualized_revenue": 1768401,
      "mcap": 8034372
    },
    {
      "rank": 12,
      "name": "Quickswap Dex",
      "symbol": "QUICK",
      "category": "Dexs",
      "tier": "HYPERLIQUID-GRADE",
      "earnings_yield_pct": 20.16,
      "annualized_revenue": 1077504,
      "mcap": 5345473
    },
    {
      "rank": 13,
      "name": "CoWSwap",
      "symbol": "COW",
      "category": "DEX Aggregator",
      "tier": "HIGH-YIELD",
      "earnings_yield_pct": 18.96,
      "annualized_revenue": 17603512,
      "mcap": 92838361
    },
    {
      "rank": 14,
      "name": "Usual USD0",
      "symbol": "USUAL",
      "category": "RWA",
      "tier": "HIGH-YIELD",
      "earnings_yield_pct": 17.84,
      "annualized_revenue": 3296911,
      "mcap": 18478294
    },
    {
      "rank": 15,
      "name": "Definitive",
      "symbol": "EDGE",
      "category": "DEX Aggregator",
      "tier": "HIGH-YIELD",
      "earnings_yield_pct": 17.51,
      "annualized_revenue": 2890240,
      "mcap": 16507645
    },
    {
      "rank": 16,
      "name": "SideShift",
      "symbol": "XAI",
      "category": "Cross Chain Bridge",
      "tier": "HIGH-YIELD",
      "earnings_yield_pct": 15.62,
      "annualized_revenue": 1776260,
      "mcap": 11371733
    },
    {
      "rank": 17,
      "name": "Graphite Protocol",
      "symbol": "GP",
      "category": "Launchpad",
      "tier": "HIGH-YIELD",
      "earnings_yield_pct": 14.67,
      "annualized_revenue": 843612,
      "mcap": 5749872
    },
    {
      "rank": 18,
      "name": "Lido",
      "symbol": "LDO",
      "category": "Liquid Staking",
      "tier": "HIGH-YIELD",
      "earnings_yield_pct": 13.26,
      "annualized_revenue": 32886099,
      "mcap": 248074705
    },
    {
      "rank": 19,
      "name": "Metaplex",
      "symbol": "MPLX",
      "category": "Launchpad",
      "tier": "HIGH-YIELD",
      "earnings_yield_pct": 13.22,
      "annualized_revenue": 1314231,
      "mcap": 9940319
    },
    {
      "rank": 20,
      "name": "deBridge",
      "symbol": "DBR",
      "category": "Bridge",
      "tier": "HIGH-YIELD",
      "earnings_yield_pct": 11.36,
      "annualized_revenue": 8836176,
      "mcap": 77760086
    },
    {
      "rank": 21,
      "name": "Geodnet",
      "symbol": "GEOD",
      "category": "Oracle",
      "tier": "HIGH-YIELD",
      "earnings_yield_pct": 11.13,
      "annualized_revenue": 10235111,
      "mcap": 91973021
    },
    {
      "rank": 22,
      "name": "OPINION",
      "symbol": "OPN",
      "category": "Prediction Market",
      "tier": "HIGH-YIELD",
      "earnings_yield_pct": 10.92,
      "annualized_revenue": 1580596,
      "mcap": 14474898
    },
    {
      "rank": 23,
      "name": "Stake DAO",
      "symbol": "SDT",
      "category": "Yield",
      "tier": "MODERATE",
      "earnings_yield_pct": 9.52,
      "annualized_revenue": 730195,
      "mcap": 7670421
    },
    {
      "rank": 24,
      "name": "Aethir",
      "symbol": "ATH",
      "category": "Developer Tools",
      "tier": "MODERATE",
      "earnings_yield_pct": 8.73,
      "annualized_revenue": 8803046,
      "mcap": 100861463
    },
    {
      "rank": 25,
      "name": "STON.fi",
      "symbol": "STON",
      "category": "Dexs",
      "tier": "MODERATE",
      "earnings_yield_pct": 8.15,
      "annualized_revenue": 1708273,
      "mcap": 20948624
    },
    {
      "rank": 26,
      "name": "AlphaLend",
      "symbol": "BLUE",
      "category": "Lending",
      "tier": "MODERATE",
      "earnings_yield_pct": 7.66,
      "annualized_revenue": 451274,
      "mcap": 5894727
    },
    {
      "rank": 27,
      "name": "World Liberty Financial",
      "symbol": "WLFI",
      "category": "Lending",
      "tier": "MODERATE",
      "earnings_yield_pct": 7.4,
      "annualized_revenue": 141819789,
      "mcap": 1915589634
    },
    {
      "rank": 28,
      "name": "Convex Finance",
      "symbol": "CVX",
      "category": "Yield",
      "tier": "MODERATE",
      "earnings_yield_pct": 6.97,
      "annualized_revenue": 8799980,
      "mcap": 126168632
    },
    {
      "rank": 29,
      "name": "Yield Basis",
      "symbol": "YB",
      "category": "Leveraged Farming",
      "tier": "MODERATE",
      "earnings_yield_pct": 6.19,
      "annualized_revenue": 1165396,
      "mcap": 18827012
    },
    {
      "rank": 30,
      "name": "Tree News",
      "symbol": "TREE",
      "category": "SoFi",
      "tier": "MODERATE",
      "earnings_yield_pct": 5.68,
      "annualized_revenue": 1002582,
      "mcap": 17642345
    },
    {
      "rank": 31,
      "name": "Aquarius Stellar",
      "symbol": "AQUA",
      "category": "Dexs",
      "tier": "LOW",
      "earnings_yield_pct": 5,
      "annualized_revenue": 762035,
      "mcap": 15245904
    },
    {
      "rank": 32,
      "name": "Pendle",
      "symbol": "PENDLE",
      "category": "Yield",
      "tier": "LOW",
      "earnings_yield_pct": 4.42,
      "annualized_revenue": 11251587,
      "mcap": 254611907
    },
    {
      "rank": 33,
      "name": "Benqi Lending",
      "symbol": "QI",
      "category": "Lending",
      "tier": "LOW",
      "earnings_yield_pct": 4.3,
      "annualized_revenue": 433863,
      "mcap": 10085827
    },
    {
      "rank": 34,
      "name": "Jupiter Aggregator",
      "symbol": "JUP",
      "category": "DEX Aggregator",
      "tier": "LOW",
      "earnings_yield_pct": 3.85,
      "annualized_revenue": 25025106,
      "mcap": 649637681
    },
    {
      "rank": 35,
      "name": "Ekubo",
      "symbol": "EKUBO",
      "category": "Dexs",
      "tier": "LOW",
      "earnings_yield_pct": 3.77,
      "annualized_revenue": 192294,
      "mcap": 5101325
    },
    {
      "rank": 36,
      "name": "Hegic",
      "symbol": "HEGIC",
      "category": "Options",
      "tier": "LOW",
      "earnings_yield_pct": 3.41,
      "annualized_revenue": 487920,
      "mcap": 14318243
    },
    {
      "rank": 37,
      "name": "SSV Network",
      "symbol": "SSV",
      "category": "Staking Pool",
      "tier": "LOW",
      "earnings_yield_pct": 3.36,
      "annualized_revenue": 1178488,
      "mcap": 35104639
    },
    {
      "rank": 38,
      "name": "Capx AI",
      "symbol": "CAPX",
      "category": "AI Agents",
      "tier": "LOW",
      "earnings_yield_pct": 3.29,
      "annualized_revenue": 521038,
      "mcap": 15847934
    },
    {
      "rank": 39,
      "name": "Treehouse Protocol",
      "symbol": "TREE",
      "category": "DOR",
      "tier": "LOW",
      "earnings_yield_pct": 3.16,
      "annualized_revenue": 231921,
      "mcap": 7333863
    },
    {
      "rank": 40,
      "name": "Banana Gun",
      "symbol": "BANANA",
      "category": "Telegram Bot",
      "tier": "LOW",
      "earnings_yield_pct": 2.94,
      "annualized_revenue": 359160,
      "mcap": 12201790
    },
    {
      "rank": 41,
      "name": "Renzo",
      "symbol": "REZ",
      "category": "Liquid Restaking",
      "tier": "LOW",
      "earnings_yield_pct": 2.57,
      "annualized_revenue": 742945,
      "mcap": 28953292
    },
    {
      "rank": 42,
      "name": "Stader",
      "symbol": "SD",
      "category": "Liquid Staking",
      "tier": "LOW",
      "earnings_yield_pct": 2.53,
      "annualized_revenue": 259722,
      "mcap": 10269299
    },
    {
      "rank": 43,
      "name": "MorpheusAI",
      "symbol": "MOR",
      "category": "AI Agents",
      "tier": "LOW",
      "earnings_yield_pct": 2.26,
      "annualized_revenue": 404955,
      "mcap": 17951019
    },
    {
      "rank": 44,
      "name": "Railgun",
      "symbol": "RAIL",
      "category": "Privacy",
      "tier": "LOW",
      "earnings_yield_pct": 2.07,
      "annualized_revenue": 3557643,
      "mcap": 171471869
    },
    {
      "rank": 45,
      "name": "Osmosis DEX",
      "symbol": "OSMO",
      "category": "Dexs",
      "tier": "LOW",
      "earnings_yield_pct": 2.06,
      "annualized_revenue": 730986,
      "mcap": 35495249
    },
    {
      "rank": 46,
      "name": "Layer3",
      "symbol": "L3",
      "category": "Foundation",
      "tier": "LOW",
      "earnings_yield_pct": 1.99,
      "annualized_revenue": 213270,
      "mcap": 10700140
    },
    {
      "rank": 47,
      "name": "Goldfinch",
      "symbol": "GFI",
      "category": "RWA Lending",
      "tier": "LOW",
      "earnings_yield_pct": 1.91,
      "annualized_revenue": 128930,
      "mcap": 6750587
    },
    {
      "rank": 48,
      "name": "Hydration DEX",
      "symbol": "HDX",
      "category": "Dexs",
      "tier": "LOW",
      "earnings_yield_pct": 1.33,
      "annualized_revenue": 320677,
      "mcap": 24098226
    },
    {
      "rank": 49,
      "name": "Virtuals Protocol",
      "symbol": "VIRTUAL",
      "category": "AI Agents",
      "tier": "LOW",
      "earnings_yield_pct": 1.2,
      "annualized_revenue": 4958622,
      "mcap": 414904602
    },
    {
      "rank": 50,
      "name": "PinkSale",
      "symbol": "PINKSALE",
      "category": "Launchpad",
      "tier": "LOW",
      "earnings_yield_pct": 1.18,
      "annualized_revenue": 252592,
      "mcap": 21457216
    },
    {
      "rank": 51,
      "name": "OpenLedger",
      "symbol": "OPEN",
      "category": "Decentralized AI",
      "tier": "LOW",
      "earnings_yield_pct": 1.18,
      "annualized_revenue": 640271,
      "mcap": 54303828
    },
    {
      "rank": 52,
      "name": "Nexus Mutual",
      "symbol": "NXM",
      "category": "Insurance",
      "tier": "LOW",
      "earnings_yield_pct": 1.15,
      "annualized_revenue": 956665,
      "mcap": 82867072
    },
    {
      "rank": 53,
      "name": "Momentum",
      "symbol": "MMT",
      "category": "Dexs",
      "tier": "LOW",
      "earnings_yield_pct": 1,
      "annualized_revenue": 286622,
      "mcap": 28557298
    },
    {
      "rank": 54,
      "name": "Axie Infinity",
      "symbol": "AXS",
      "category": "Gaming",
      "tier": "LOW",
      "earnings_yield_pct": 0.94,
      "annualized_revenue": 1641709,
      "mcap": 174211384
    },
    {
      "rank": 55,
      "name": "Arbitrum",
      "symbol": "ARB",
      "category": "Canonical Bridge",
      "tier": "LOW",
      "earnings_yield_pct": 0.93,
      "annualized_revenue": 5068074,
      "mcap": 547502442
    },
    {
      "rank": 56,
      "name": "HumidiFi",
      "symbol": "WET",
      "category": "Dexs",
      "tier": "LOW",
      "earnings_yield_pct": 0.84,
      "annualized_revenue": 118710,
      "mcap": 14117123
    },
    {
      "rank": 57,
      "name": "Bitway Earn",
      "symbol": "BTW",
      "category": "Basis Trading",
      "tier": "LOW",
      "earnings_yield_pct": 0.75,
      "annualized_revenue": 1143521,
      "mcap": 153004989
    },
    {
      "rank": 58,
      "name": "ENS",
      "symbol": "ENS",
      "category": "Domains",
      "tier": "LOW",
      "earnings_yield_pct": 0.73,
      "annualized_revenue": 1606791,
      "mcap": 220774346
    },
    {
      "rank": 59,
      "name": "Illuvium",
      "symbol": "ILV",
      "category": "Gaming",
      "tier": "LOW",
      "earnings_yield_pct": 0.71,
      "annualized_revenue": 199314,
      "mcap": 28241276
    },
    {
      "rank": 60,
      "name": "Olympus DAO",
      "symbol": "OHM",
      "category": "Reserve Currency",
      "tier": "LOW",
      "earnings_yield_pct": 0.7,
      "annualized_revenue": 1679998,
      "mcap": 240240984
    }
  ]
}